opentelemetry/instrumentation/psycopg/__init__.py
opentelemetry/instrumentation/psycopg/package.py
opentelemetry/instrumentation/psycopg/py.typed
opentelemetry/instrumentation/psycopg/version.py
opentelemetry_instrumentation_psycopg-0.60b1.dist-info/METADATA
opentelemetry_instrumentation_psycopg-0.60b1.dist-info/WHEEL
opentelemetry_instrumentation_psycopg-0.60b1.dist-info/entry_points.txt
opentelemetry_instrumentation_psycopg-0.60b1.dist-info/licenses/LICENSE
opentelemetry_instrumentation_psycopg-0.60b1.dist-info/RECORD
