Metadata-Version: 2.4
Name: opentelemetry-instrumentation-psycopg
Version: 0.60b1
Summary: OpenTelemetry psycopg instrumentation
Project-URL: Homepage, https://github.com/open-telemetry/opentelemetry-python-contrib/tree/main/instrumentation/opentelemetry-instrumentation-psycopg
Project-URL: Repository, https://github.com/open-telemetry/opentelemetry-python-contrib
Author-email: OpenTelemetry Authors <cncf-opentelemetry-contributors@lists.cncf.io>
License-Expression: Apache-2.0
License-File: LICENSE
Classifier: Development Status :: 4 - Beta
Classifier: Intended Audience :: Developers
Classifier: License :: OSI Approved :: Apache Software License
Classifier: Programming Language :: Python
Classifier: Programming Language :: Python :: 3
Classifier: Programming Language :: Python :: 3.9
Classifier: Programming Language :: Python :: 3.10
Classifier: Programming Language :: Python :: 3.11
Classifier: Programming Language :: Python :: 3.12
Classifier: Programming Language :: Python :: 3.13
Requires-Python: >=3.9
Requires-Dist: opentelemetry-api~=1.12
Requires-Dist: opentelemetry-instrumentation-dbapi==0.60b1
Requires-Dist: opentelemetry-instrumentation==0.60b1
Provides-Extra: instruments
Requires-Dist: psycopg>=3.1.0; extra == 'instruments'
